MANIFEST.in
Readme.md
requirements.txt
requirements_setuptools.txt
requirements_test.txt
setup.cfg
setup.py
/home/kjensen/dx-toolkit/src/python/scripts/dx-clone-asset
/home/kjensen/dx-toolkit/src/python/scripts/dx-docker
/home/kjensen/dx-toolkit/src/python/scripts/dx-download-all-inputs
/home/kjensen/dx-toolkit/src/python/scripts/dx-fetch-bundled-depends
/home/kjensen/dx-toolkit/src/python/scripts/dx-generate-dxapp
/home/kjensen/dx-toolkit/src/python/scripts/dx-jobutil-add-output
/home/kjensen/dx-toolkit/src/python/scripts/dx-jobutil-dxlink
/home/kjensen/dx-toolkit/src/python/scripts/dx-jobutil-get-identity-token
/home/kjensen/dx-toolkit/src/python/scripts/dx-jobutil-new-job
/home/kjensen/dx-toolkit/src/python/scripts/dx-jobutil-parse-link
/home/kjensen/dx-toolkit/src/python/scripts/dx-jobutil-report-error
/home/kjensen/dx-toolkit/src/python/scripts/dx-log-stream
/home/kjensen/dx-toolkit/src/python/scripts/dx-mount-all-inputs
/home/kjensen/dx-toolkit/src/python/scripts/dx-notebook-reconnect
/home/kjensen/dx-toolkit/src/python/scripts/dx-print-bash-vars
/home/kjensen/dx-toolkit/src/python/scripts/dx-upload-all-outputs
dxpy/__init__.py
dxpy/api.py
dxpy/app_builder.py
dxpy/app_categories.py
dxpy/asset_builder.py
dxpy/compat.py
dxpy/dxlog.py
dxpy/exceptions.py
dxpy/executable_builder.py
dxpy/ssh_tunnel_app_support.py
dxpy/system_requirements.py
dxpy/toolkit_version.py
dxpy/workflow_builder.py
dxpy.egg-info/PKG-INFO
dxpy.egg-info/SOURCES.txt
dxpy.egg-info/dependency_links.txt
dxpy.egg-info/entry_points.txt
dxpy.egg-info/not-zip-safe
dxpy.egg-info/requires.txt
dxpy.egg-info/top_level.txt
dxpy/bindings/__init__.py
dxpy/bindings/auth.py
dxpy/bindings/download_all_inputs.py
dxpy/bindings/dxanalysis.py
dxpy/bindings/dxapp.py
dxpy/bindings/dxapp_container_functions.py
dxpy/bindings/dxapplet.py
dxpy/bindings/dxdatabase.py
dxpy/bindings/dxdatabase_functions.py
dxpy/bindings/dxdataobject_functions.py
dxpy/bindings/dxfile.py
dxpy/bindings/dxfile_functions.py
dxpy/bindings/dxglobalworkflow.py
dxpy/bindings/dxjob.py
dxpy/bindings/dxproject.py
dxpy/bindings/dxrecord.py
dxpy/bindings/dxworkflow.py
dxpy/bindings/mount_all_inputs.py
dxpy/bindings/search.py
