Metadata-Version: 2.1
Name: dxpy
Version: 0.403.0
Summary: DNAnexus Platform API bindings for Python
Home-page: https://github.com/dnanexus/dx-toolkit
Author: Aleksandra Zalcman, Andrey Kislyuk, Anurag Biyani, Geet Duggal, Katherine Lai, Kurt Jensen, Marek Hrvol, Ohad Rodeh, Phil Sung
Author-email: support@dnanexus.com
License: Apache Software License
Classifier: Environment :: Console
Classifier: Intended Audience :: Developers
Classifier: License :: OSI Approved :: Apache Software License
Classifier: Operating System :: MacOS :: MacOS X
Classifier: Operating System :: POSIX
Classifier: Programming Language :: Python
Classifier: Programming Language :: Unix Shell
Classifier: Topic :: Software Development :: Libraries :: Python Modules
Requires-Python: >=3.8
Requires-Dist: argcomplete>=2.0.0; python_version >= "3.10"
Requires-Dist: argcomplete<2.0.0,>=1.9.4; python_version < "3.10"
Requires-Dist: websocket-client<1.8.0,>=1.6.0
Requires-Dist: python-dateutil>=2.5
Requires-Dist: psutil>=5.9.3
Requires-Dist: certifi>=2024.7.4
Requires-Dist: urllib3<2.2,>=1.25
Requires-Dist: pyreadline3==3.4.1; sys_platform == "win32"
Requires-Dist: colorama<=0.4.6,>=0.4.4; sys_platform == "win32"
Requires-Dist: crc32c>=2.7.1
Requires-Dist: awscrt>=0.23.4
Provides-Extra: pandas
Requires-Dist: pandas==1.3.5; extra == "pandas"
Requires-Dist: numpy<2.0.0; extra == "pandas"
Provides-Extra: xattr
Requires-Dist: xattr==0.10.1; (sys_platform == "linux2" or sys_platform == "linux") and extra == "xattr"
